{
  "version": 1,
  "name": "main-cat",
  "image": "source/01_cat_multiple_expression_variations.png",
  "defaultFps": 8,
  "hitAlphaThreshold": 24,
  "frames": [
    { "x": 85, "y": 122, "width": 327, "height": 353 },
    { "x": 613, "y": 122, "width": 321, "height": 353 },
    { "x": 84, "y": 603, "width": 296, "height": 325 },
    { "x": 621, "y": 683, "width": 344, "height": 236 },
    { "x": 613, "y": 122, "width": 321, "height": 353 },
    { "x": 85, "y": 122, "width": 327, "height": 353 },
    { "x": 621, "y": 683, "width": 344, "height": 236 },
    { "x": 84, "y": 603, "width": 296, "height": 325 }
  ],
  "states": {
    "idle": {
      "frames": [0, 1, 0, 3, 0, 4, 0, 6],
      "fps": 3,
      "loop": true
    },
    "walk": {
      "frames": [2, 1, 0, 4, 2, 6, 7, 5],
      "fps": 9,
      "loop": true
    },
    "jump": {
      "frames": [1, 0, 4],
      "fps": 8,
      "loop": false
    },
    "fall": {
      "frames": [6, 3, 7],
      "fps": 8,
      "loop": true
    },
    "drag": {
      "frames": [0],
      "fps": 1,
      "loop": true
    }
  }
}
